pttk/__init__.py
pttk/optimizer.py
pttk/util.py
pttk/utils.py
pttk-0.0.3.dist-info/LICENSE
pttk-0.0.3.dist-info/METADATA
pttk-0.0.3.dist-info/WHEEL
pttk-0.0.3.dist-info/top_level.txt
pttk-0.0.3.dist-info/RECORD
