Metadata-Version: 2.1
Name: pttk
Version: 0.0.3
Summary: Post-Training Toolkit
Home-page: https://github.com/leesusu/post-training-toolkit.git
Author: Xiaobo Li
Author-email: xiaobo.li.ai@gmail.com
License: UNKNOWN
Platform: UNKNOWN
Classifier: Programming Language :: Python :: 3
Classifier: License :: OSI Approved :: MIT License
Classifier: Operating System :: OS Independent
Requires-Python: >=3.6
